[
  {
    "region": "apac",
    "service": "checkout",
    "latency_ms": 192.28,
    "uptime_pct": 97.85,
    "timestamp": 20250301
  },
  {
    "region": "apac",
    "service": "catalog",
    "latency_ms": 222.03,
    "uptime_pct": 98.571,
    "timestamp": 20250302
  },
  {
    "region": "apac",
    "service": "checkout",
    "latency_ms": 216.29,
    "uptime_pct": 97.704,
    "timestamp": 20250303
  },
  {
    "region": "apac",
    "service": "catalog",
    "latency_ms": 171.42,
    "uptime_pct": 97.872,
    "timestamp": 20250304
  },
  {
    "region": "apac",
    "service": "payments",
    "latency_ms": 173.55,
    "uptime_pct": 99.281,
    "timestamp": 20250305
  },
  {
    "region": "apac",
    "service": "analytics",
    "latency_ms": 167.93,
    "uptime_pct": 97.863,
    "timestamp": 20250306
  },
  {
    "region": "apac",
    "service": "payments",
    "latency_ms": 138.9,
    "uptime_pct": 98.372,
    "timestamp": 20250307
  },
  {
    "region": "apac",
    "service": "recommendations",
    "latency_ms": 164.37,
    "uptime_pct": 99.371,
    "timestamp": 20250308
  },
  {
    "region": "apac",
    "service": "checkout",
    "latency_ms": 139.1,
    "uptime_pct": 97.516,
    "timestamp": 20250309
  },
  {
    "region": "apac",
    "service": "catalog",
    "latency_ms": 153.65,
    "uptime_pct": 98.763,
    "timestamp": 20250310
  },
  {
    "region": "apac",
    "service": "payments",
    "latency_ms": 142.51,
    "uptime_pct": 98.623,
    "timestamp": 20250311
  },
  {
    "region": "apac",
    "service": "checkout",
    "latency_ms": 213.6,
    "uptime_pct": 97.846,
    "timestamp": 20250312
  },
  {
    "region": "emea",
    "service": "recommendations",
    "latency_ms": 170.69,
    "uptime_pct": 98.185,
    "timestamp": 20250301
  },
  {
    "region": "emea",
    "service": "checkout",
    "latency_ms": 164.03,
    "uptime_pct": 99.361,
    "timestamp": 20250302
  },
  {
    "region": "emea",
    "service": "recommendations",
    "latency_ms": 143.49,
    "uptime_pct": 99.275,
    "timestamp": 20250303
  },
  {
    "region": "emea",
    "service": "analytics",
    "latency_ms": 183.74,
    "uptime_pct": 97.797,
    "timestamp": 20250304
  },
  {
    "region": "emea",
    "service": "payments",
    "latency_ms": 161.67,
    "uptime_pct": 98.02,
    "timestamp": 20250305
  },
  {
    "region": "emea",
    "service": "analytics",
    "latency_ms": 215.77,
    "uptime_pct": 98.055,
    "timestamp": 20250306
  },
  {
    "region": "emea",
    "service": "recommendations",
    "latency_ms": 123.45,
    "uptime_pct": 98.138,
    "timestamp": 20250307
  },
  {
    "region": "emea",
    "service": "analytics",
    "latency_ms": 203.44,
    "uptime_pct": 98.994,
    "timestamp": 20250308
  },
  {
    "region": "emea",
    "service": "analytics",
    "latency_ms": 173.93,
    "uptime_pct": 98.629,
    "timestamp": 20250309
  },
  {
    "region": "emea",
    "service": "support",
    "latency_ms": 170.48,
    "uptime_pct": 99.229,
    "timestamp": 20250310
  },
  {
    "region": "emea",
    "service": "catalog",
    "latency_ms": 116.19,
    "uptime_pct": 97.835,
    "timestamp": 20250311
  },
  {
    "region": "emea",
    "service": "checkout",
    "latency_ms": 199.01,
    "uptime_pct": 98.559,
    "timestamp": 20250312
  },
  {
    "region": "amer",
    "service": "payments",
    "latency_ms": 204.97,
    "uptime_pct": 98.547,
    "timestamp": 20250301
  },
  {
    "region": "amer",
    "service": "payments",
    "latency_ms": 125.69,
    "uptime_pct": 98.025,
    "timestamp": 20250302
  },
  {
    "region": "amer",
    "service": "catalog",
    "latency_ms": 144.28,
    "uptime_pct": 98.767,
    "timestamp": 20250303
  },
  {
    "region": "amer",
    "service": "analytics",
    "latency_ms": 111.64,
    "uptime_pct": 98.402,
    "timestamp": 20250304
  },
  {
    "region": "amer",
    "service": "payments",
    "latency_ms": 191.47,
    "uptime_pct": 99.052,
    "timestamp": 20250305
  },
  {
    "region": "amer",
    "service": "payments",
    "latency_ms": 177.08,
    "uptime_pct": 98.761,
    "timestamp": 20250306
  },
  {
    "region": "amer",
    "service": "recommendations",
    "latency_ms": 134.95,
    "uptime_pct": 98.584,
    "timestamp": 20250307
  },
  {
    "region": "amer",
    "service": "recommendations",
    "latency_ms": 164.19,
    "uptime_pct": 98.867,
    "timestamp": 20250308
  },
  {
    "region": "amer",
    "service": "support",
    "latency_ms": 184.67,
    "uptime_pct": 99.035,
    "timestamp": 20250309
  },
  {
    "region": "amer",
    "service": "recommendations",
    "latency_ms": 141.07,
    "uptime_pct": 98.079,
    "timestamp": 20250310
  },
  {
    "region": "amer",
    "service": "support",
    "latency_ms": 161.25,
    "uptime_pct": 98.634,
    "timestamp": 20250311
  },
  {
    "region": "amer",
    "service": "checkout",
    "latency_ms": 207.19,
    "uptime_pct": 98.296,
    "timestamp": 20250312
  }
]